reelsWatchBot/__init__.py
reelsWatchBot/reelsWatchBot.py
reelswatchbot-0.0.30.dist-info/METADATA
reelswatchbot-0.0.30.dist-info/WHEEL
reelswatchbot-0.0.30.dist-info/top_level.txt
reelswatchbot-0.0.30.dist-info/RECORD
